pyupgrade_directories/__init__.py
pyupgrade_directories/__main__.py
pyupgrade_directories/py.typed
pyupgrade_directories-0.3.0.dist-info/LICENSE
pyupgrade_directories-0.3.0.dist-info/METADATA
pyupgrade_directories-0.3.0.dist-info/WHEEL
pyupgrade_directories-0.3.0.dist-info/entry_points.txt
pyupgrade_directories-0.3.0.dist-info/RECORD
