Metadata-Version: 2.1
Name: pyupgrade-directories
Version: 0.3.0
Summary: Run pyupgrade on all files in a directory, and optionally recursively.
Author-email: Dominic Davis-Foster <dominic@davis-foster.co.uk>
License: MIT
Keywords: linting,pyupgrade,utility
Home-page: https://github.com/domdfcoding/pyupgrade-directories
Project-URL: Issue Tracker, https://github.com/domdfcoding/pyupgrade-directories/issues
Project-URL: Source Code, https://github.com/domdfcoding/pyupgrade-directories
Platform: Windows
Platform: macOS
Platform: Linux
Classifier: Development Status :: 4 - Beta
Classifier: Environment :: Console
Classifier: Intended Audience :: Developers
Classifier: License :: OSI Approved :: MIT License
Classifier: Operating System :: OS Independent
Classifier: Programming Language :: Python
Classifier: Programming Language :: Python :: 3 :: Only
Classifier: Programming Language :: Python :: 3.6
Classifier: Programming Language :: Python :: 3.7
Classifier: Programming Language :: Python :: 3.8
Classifier: Programming Language :: Python :: 3.9
Classifier: Programming Language :: Python :: 3.10
Classifier: Programming Language :: Python :: Implementation :: CPython
Classifier: Programming Language :: Python :: Implementation :: PyPy
Classifier: Topic :: Software Development
Classifier: Topic :: Utilities
Classifier: Typing :: Typed
Requires-Python: >=3.6
Requires-Dist: pyupgrade>=2.5.0
